setup_client.py
cli/__init__.py
cli/client.py
cli/client/__init__.py
cli/client/client_db.py
cli/client/client_gui.py
cli/client/main_window.py
cli/client/transport.py
cli/common/__init__.py
cli/common/decos.py
cli/common/discripts.py
cli/common/errors.py
cli/common/metaclasses.py
cli/common/utils.py
cli/common/variables.py
cli/doc/__init__.py
cli/doc/source/__init__.py
cli/doc/source/conf.py
cli/log/__init__.py
cli/log/config_client.py
cli/log/config_server.py
cli/unit_tests/__init__.py
cli/unit_tests/test_client.py
cli/unit_tests/test_server.py
cli/unit_tests/test_utils.py
message_client_learning_proj.egg-info/PKG-INFO
message_client_learning_proj.egg-info/SOURCES.txt
message_client_learning_proj.egg-info/dependency_links.txt
message_client_learning_proj.egg-info/requires.txt
message_client_learning_proj.egg-info/top_level.txt