Metadata-Version: 1.0
Name: message-client-learning-proj
Version: 0.0.1
Summary: message_client_learning_proj
Home-page: UNKNOWN
Author: Alexandr Nikiforov
Author-email: 8712060@gmail.com
License: UNKNOWN
Platform: UNKNOWN
